MANIFEST.in
setup.py
sqlalchemy_postgresql_json/__init__.py
sqlalchemy_postgresql_json/ltree.py
sqlalchemy_postgresql_json/mutable.py
sqlalchemy_postgresql_json/pgjson.py
sqlalchemy_postgresql_json.egg-info/PKG-INFO
sqlalchemy_postgresql_json.egg-info/SOURCES.txt
sqlalchemy_postgresql_json.egg-info/dependency_links.txt
sqlalchemy_postgresql_json.egg-info/not-zip-safe
sqlalchemy_postgresql_json.egg-info/requires.txt
sqlalchemy_postgresql_json.egg-info/top_level.txt