Metadata-Version: 1.1
Name: sqlalchemy-postgresql-json
Version: 0.5.0
Summary: Postgresql JSON Extension for sqlalchemy
Home-page: https://github.com/DisruptiveLabs/sqlalchemy_postgresql_json
Author: Franklyn Tackitt
Author-email: franklyn@tackitt.net
License: UNKNOWN
Download-URL: https://github.com/DisruptiveLabs/sqlalchemy_postgresql_json/tarball/0.5.0
Platform: UNKNOWN
